CHANGELOG.txt
LICENSE.txt
MANIFEST.in
README.txt
setup.py
cc.egg-info/SOURCES.txt
cc.egg-info/dependency_links.txt
cc.egg-info/top_level.txt
ccddegefg.egg-info/PKG-INFO
ccddegefg.egg-info/SOURCES.txt
ccddegefg.egg-info/dependency_links.txt
ccddegefg.egg-info/top_level.txt
helloworld/__init__.py